codeppr/cli.py
codeppr/configure.py
codeppr/display.py
codeppr/git_helper.py
codeppr/main.py
codeppr/reviewer.py
codeppr/state.py
codeppr/tools.py
codeppr/auth/keys.py
codeppr/auth/providers.py
codeppr-0.1.4.dist-info/licenses/LICENSE
codeppr-0.1.4.dist-info/METADATA
codeppr-0.1.4.dist-info/WHEEL
codeppr-0.1.4.dist-info/entry_points.txt
codeppr-0.1.4.dist-info/top_level.txt
codeppr-0.1.4.dist-info/RECORD
