Metadata-Version: 2.4
Name: codeppr
Version: 0.1.4
Summary: An AI-assisted code review agent that saves you from bad commits by running its analysis during the pre-commit stage.
Author: Piyush Gupta
License: Apache-2.0
Project-URL: Repository, https://github.com/fampiyush/codeppr
Requires-Python: >=3.12
License-File: LICENSE
Requires-Dist: click>=8.3.1
Requires-Dist: keyring>=25.7.0
Requires-Dist: keyrings-alt>=5.0.2
Requires-Dist: langchain>=1.2.2
Requires-Dist: langchain-anthropic>=1.3.1
Requires-Dist: langchain-google-genai>=4.1.3
Requires-Dist: langchain-openai>=1.1.7
Requires-Dist: platformdirs>=4.5.1
Requires-Dist: pydantic>=2.12.5
Dynamic: license-file
